worldOfGames/Live.py
worldOfGames/__init__.py
worldOfGames/games/__init__.py
worldOfGames/games/currency_roulette.py
worldOfGames/games/game_helper.py
worldOfGames/games/guess_game.py
worldOfGames/games/memory_game.py
worldOfGames-0.0.9.dist-info/METADATA
worldOfGames-0.0.9.dist-info/WHEEL
worldOfGames-0.0.9.dist-info/top_level.txt
worldOfGames-0.0.9.dist-info/RECORD
