Metadata-Version: 2.1
Name: worldOfGames
Version: 0.0.9
Summary: world of games
Home-page: UNKNOWN
License: UNKNOWN
Keywords: python,devops course,memory game,guessing game
Platform: UNKNOWN
Classifier: Programming Language :: Python :: 3
Classifier: Operating System :: Unix
Classifier: Operating System :: MacOS :: MacOS X
Classifier: Operating System :: Microsoft :: Windows
Requires-Dist: forex-python
